ansi_parser.py
config.py
kdebbsclient.py
telnet_client.py
ui/__init__.py
ui/bbs_chooser.py
ui/config_dialog.py
ui/terminal_window.py
kde_bbs_client-0.1.5.dist-info/METADATA
kde_bbs_client-0.1.5.dist-info/WHEEL
kde_bbs_client-0.1.5.dist-info/entry_points.txt
kde_bbs_client-0.1.5.dist-info/RECORD
