Metadata-Version: 2.4
Name: kde-bbs-client
Version: 0.1.5
Summary: A modern KDE client for old school telnet based BBS systems
Requires-Python: >=3.10
Requires-Dist: pyside6>=6.4.0
Requires-Dist: pyyaml>=6.0
Provides-Extra: dev
Requires-Dist: ruff>=0.1.0; extra == 'dev'
